odoo10_addon_base_locale_uom_default-10.0.1.0.0-py2.7-nspkg.pth
odoo/addons/base_locale_uom_default/README.rst
odoo/addons/base_locale_uom_default/__init__.py
odoo/addons/base_locale_uom_default/__manifest__.py
odoo/addons/base_locale_uom_default/demo/res_lang_demo.xml
odoo/addons/base_locale_uom_default/models/__init__.py
odoo/addons/base_locale_uom_default/models/res_lang.py
odoo/addons/base_locale_uom_default/tests/__init__.py
odoo/addons/base_locale_uom_default/tests/test_res_lang.py
odoo/addons/base_locale_uom_default/views/res_lang_view.xml
odoo10_addon_base_locale_uom_default-10.0.1.0.0.dist-info/DESCRIPTION.rst
odoo10_addon_base_locale_uom_default-10.0.1.0.0.dist-info/METADATA
odoo10_addon_base_locale_uom_default-10.0.1.0.0.dist-info/RECORD
odoo10_addon_base_locale_uom_default-10.0.1.0.0.dist-info/WHEEL
odoo10_addon_base_locale_uom_default-10.0.1.0.0.dist-info/metadata.json
odoo10_addon_base_locale_uom_default-10.0.1.0.0.dist-info/namespace_packages.txt
odoo10_addon_base_locale_uom_default-10.0.1.0.0.dist-info/top_level.txt
